{"Aceh":{"name":"Aceh","gdp_tn_idr":207,"population":5371500,"unemployment_rate":6,"hdi":0.726,"gdp_year":2022,"unemployment_year":2023,"hdi_year":2023,"gdp_per_capita_idr":38536722},"Sumatera Utara":{"name":"Sumatera Utara","gdp_tn_idr":758,"population":15115100,"unemployment_rate":5.9,"hdi":0.729,"gdp_year":2022,"unemployment_year":2023,"hdi_year":2023,"gdp_per_capita_idr":50148527},"Sumatera Barat":{"name":"Sumatera Barat","gdp_tn_idr":253,"population":5640600,"unemployment_rate":5.9,"hdi":0.736,"gdp_year":2022,"unemployment_year":2023,"hdi_year":2023,"gdp_per_capita_idr":44853384},"Riau":{"name":"Riau","gdp_tn_idr":674,"population":6998300,"unemployment_rate":4.2,"hdi":0.73,"gdp_year":2022,"unemployment_year":2023,"hdi_year":2023,"gdp_per_capita_idr":96309104},"Jambi":{"name":"Jambi","gdp_tn_idr":198,"population":3685800,"unemployment_rate":4.5,"hdi":0.718,"gdp_year":2022,"unemployment_year":2023,"hdi_year":2023,"gdp_per_capita_idr":53719681},"Sumatera Selatan":{"name":"Sumatera Selatan","gdp_tn_idr":484,"population":8602100,"unemployment_rate":4.1,"hdi":0.711,"gdp_year":2022,"unemployment_year":2023,"hdi_year":2023,"gdp_per_capita_idr":56265331},"Bengkulu":{"name":"Bengkulu","gdp_tn_idr":71,"population":2067000,"unemployment_rate":3.4,"hdi":0.717,"gdp_year":2022,"unemployment_year":2023,"hdi_year":2023,"gdp_per_capita_idr":34349299},"Lampung":{"name":"Lampung","gdp_tn_idr":349,"population":9176100,"unemployment_rate":4.2,"hdi":0.697,"gdp_year":2022,"unemployment_year":2023,"hdi_year":2023,"gdp_per_capita_idr":38033587},"Bangka-Belitung":{"name":"Bangka-Belitung","gdp_tn_idr":71,"population":1517800,"unemployment_rate":4.6,"hdi":0.717,"gdp_year":2022,"unemployment_year":2023,"hdi_year":2023,"gdp_per_capita_idr":46778232},"Kepulauan Riau":{"name":"Kepulauan Riau","gdp_tn_idr":277,"population":2247600,"unemployment_rate":6.8,"hdi":0.766,"gdp_year":2022,"unemployment_year":2023,"hdi_year":2023,"gdp_per_capita_idr":123242570},"Jakarta Raya":{"name":"DKI Jakarta","gdp_tn_idr":2968,"population":10679900,"unemployment_rate":6.5,"hdi":0.823,"gdp_year":2022,"unemployment_year":2023,"hdi_year":2023,"gdp_per_capita_idr":277905224},"Jawa Barat":{"name":"Jawa Barat","gdp_tn_idr":2249,"population":49935700,"unemployment_rate":7.4,"hdi":0.724,"gdp_year":2022,"unemployment_year":2023,"hdi_year":2023,"gdp_per_capita_idr":45037919},"Jawa Tengah":{"name":"Jawa Tengah","gdp_tn_idr":1337,"population":37032400,"unemployment_rate":5.1,"hdi":0.727,"gdp_year":2022,"unemployment_year":2023,"hdi_year":2023,"gdp_per_capita_idr":36103520},"Yogyakarta":{"name":"DI Yogyakarta","gdp_tn_idr":131,"population":3939300,"unemployment_rate":3.7,"hdi":0.802,"gdp_year":2022,"unemployment_year":2023,"hdi_year":2023,"gdp_per_capita_idr":33254639},"Jawa Timur":{"name":"Jawa Timur","gdp_tn_idr":2319,"population":40665600,"unemployment_rate":4.9,"hdi":0.73,"gdp_year":2022,"unemployment_year":2023,"hdi_year":2023,"gdp_per_capita_idr":57026086},"Banten":{"name":"Banten","gdp_tn_idr":685,"population":12398600,"unemployment_rate":7.5,"hdi":0.729,"gdp_year":2022,"unemployment_year":2023,"hdi_year":2023,"gdp_per_capita_idr":55248173},"Bali":{"name":"Bali","gdp_tn_idr":222,"population":4380800,"unemployment_rate":2.7,"hdi":0.769,"gdp_year":2022,"unemployment_year":2023,"hdi_year":2023,"gdp_per_capita_idr":50675676},"Nusa Tenggara Barat":{"name":"Nusa Tenggara Barat","gdp_tn_idr":152,"population":5431900,"unemployment_rate":2.8,"hdi":0.688,"gdp_year":2022,"unemployment_year":2023,"hdi_year":2023,"gdp_per_capita_idr":27982842},"Nusa Tenggara Timur":{"name":"Nusa Tenggara Timur","gdp_tn_idr":107,"population":5605300,"unemployment_rate":3.1,"hdi":0.658,"gdp_year":2022,"unemployment_year":2023,"hdi_year":2023,"gdp_per_capita_idr":19089076},"Kalimantan Barat":{"name":"Kalimantan Barat","gdp_tn_idr":186,"population":5453300,"unemployment_rate":4.8,"hdi":0.688,"gdp_year":2022,"unemployment_year":2023,"hdi_year":2023,"gdp_per_capita_idr":34107788},"Kalimantan Tengah":{"name":"Kalimantan Tengah","gdp_tn_idr":143,"population":2769200,"unemployment_rate":3.8,"hdi":0.713,"gdp_year":2022,"unemployment_year":2023,"hdi_year":2023,"gdp_per_capita_idr":51639463},"Kalimantan Selatan":{"name":"Kalimantan Selatan","gdp_tn_idr":172,"population":4188800,"unemployment_rate":4.3,"hdi":0.709,"gdp_year":2022,"unemployment_year":2023,"hdi_year":2023,"gdp_per_capita_idr":41061879},"Kalimantan Timur":{"name":"Kalimantan Timur","gdp_tn_idr":651,"population":3898200,"unemployment_rate":5.3,"hdi":0.769,"gdp_year":2022,"unemployment_year":2023,"hdi_year":2023,"gdp_per_capita_idr":167000154},"Sulawesi Utara":{"name":"Sulawesi Utara","gdp_tn_idr":137,"population":2639300,"unemployment_rate":6.1,"hdi":0.738,"gdp_year":2022,"unemployment_year":2023,"hdi_year":2023,"gdp_per_capita_idr":51907703},"Sulawesi Tengah":{"name":"Sulawesi Tengah","gdp_tn_idr":211,"population":3068800,"unemployment_rate":2.9,"hdi":0.697,"gdp_year":2022,"unemployment_year":2023,"hdi_year":2023,"gdp_per_capita_idr":68756517},"Sulawesi Selatan":{"name":"Sulawesi Selatan","gdp_tn_idr":518,"population":9206200,"unemployment_rate":4.3,"hdi":0.72,"gdp_year":2022,"unemployment_year":2023,"hdi_year":2023,"gdp_per_capita_idr":56266429},"Sulawesi Tenggara":{"name":"Sulawesi Tenggara","gdp_tn_idr":140,"population":2753600,"unemployment_rate":3,"hdi":0.7,"gdp_year":2022,"unemployment_year":2023,"hdi_year":2023,"gdp_per_capita_idr":50842533},"Gorontalo":{"name":"Gorontalo","gdp_tn_idr":41,"population":1246600,"unemployment_rate":3.1,"hdi":0.684,"gdp_year":2022,"unemployment_year":2023,"hdi_year":2023,"gdp_per_capita_idr":32889459},"Sulawesi Barat":{"name":"Sulawesi Barat","gdp_tn_idr":51,"population":1437200,"unemployment_rate":2.3,"hdi":0.666,"gdp_year":2022,"unemployment_year":2023,"hdi_year":2023,"gdp_per_capita_idr":35485667},"Maluku":{"name":"Maluku","gdp_tn_idr":55,"population":1869400,"unemployment_rate":6.7,"hdi":0.699,"gdp_year":2022,"unemployment_year":2023,"hdi_year":2023,"gdp_per_capita_idr":29421205},"Maluku Utara":{"name":"Maluku Utara","gdp_tn_idr":46,"population":1316500,"unemployment_rate":4.2,"hdi":0.693,"gdp_year":2022,"unemployment_year":2023,"hdi_year":2023,"gdp_per_capita_idr":34941132},"Papua Barat":{"name":"Papua Barat","gdp_tn_idr":69,"population":1149400,"unemployment_rate":5.3,"hdi":0.657,"gdp_year":2022,"unemployment_year":2023,"hdi_year":2023,"gdp_per_capita_idr":60031321},"Papua":{"name":"Papua","gdp_tn_idr":222,"population":4468800,"unemployment_rate":2.7,"hdi":0.607,"gdp_year":2022,"unemployment_year":2023,"hdi_year":2023,"gdp_per_capita_idr":49677766}}